{"/.deco/blocks/app-shopify.json":{"blockType":"apps","__resolveType":"decohub/apps/app-shopify.ts"},"/.deco/blocks/AsideMenu.json":{"blockType":"sections","__resolveType":"site/sections/Institutional/AsideMenu.tsx"},"/.deco/blocks/Banner%20Secund%C3%A1rio%20-%20Categorias.json":{"blockType":"sections","__resolveType":"site/sections/Container.tsx"},"/.deco/blocks/Banners%20Terci%C3%A1rio%20-%20Grid.json":{"blockType":"sections","__resolveType":"site/sections/Container.tsx"},"/.deco/blocks/Categoria%20-%20Banner.json":{"blockType":"sections","__resolveType":"site/sections/Category/CategoryBanner.tsx"},"/.deco/blocks/Categoria%20-%20Breadcrumb.json":{"blockType":"sections","__resolveType":"site/sections/Container.tsx"},"/.deco/blocks/deco-blog.json":{"blockType":"apps","__resolveType":"site/apps/deco/blog.ts"},"/.deco/blocks/deco-htmx.json":{"blockType":"apps","__resolveType":"site/apps/deco/htmx.ts"},"/.deco/blocks/deco-shopify.json":{"blockType":"apps","__resolveType":"site/apps/deco/shopify.ts"},"/.deco/blocks/Footer%20Global.json":{"blockType":"sections","__resolveType":"site/sections/Container.tsx"},"/.deco/blocks/Footer.json":{"blockType":"sections","__resolveType":"site/sections/Footer.tsx"},"/.deco/blocks/Groovy%20Vibes.json":{"blockType":"sections","__resolveType":"site/sections/Theme/Theme.tsx"},"/.deco/blocks/Header%20Global.json":{"blockType":"sections","__resolveType":"site/sections/Container.tsx"},"/.deco/blocks/Home%20-%20Prateleira%20Cole%C3%A7%C3%A3o.json":{"blockType":"sections","__resolveType":"site/sections/Container.tsx"},"/.deco/blocks/htmx.json":{"blockType":"apps","__resolveType":"decohub/apps/htmx.ts"},"/.deco/blocks/Neutral.json":{"blockType":"sections","__resolveType":"site/sections/Theme/Theme.tsx"},"/.deco/blocks/pages-Category-137950.json":{"name":"Category","path":"/*","blockType":"pages","__resolveType":"website/pages/Page.tsx"},"/.deco/blocks/pages-Formas%2520de%2520Pagamento-68246.json":{"name":"Formas de Pagamento","path":"/institucional/formas-pagamento","blockType":"pages","__resolveType":"website/pages/Page.tsx"},"/.deco/blocks/pages-My%2520New%2520Page-652075.json":{"name":"Garantia","path":"/institucional/garantia","blockType":"pages","__resolveType":"website/pages/Page.tsx"},"/.deco/blocks/pages-My%2520New%2520Page-740761.json":{"name":"Quem Somos","path":"/institucional/quem-somos","blockType":"pages","__resolveType":"website/pages/Page.tsx"},"/.deco/blocks/pages-Offline-310215.json":{"name":"Offline","path":"/offline","blockType":"pages","__resolveType":"website/pages/Page.tsx"},"/.deco/blocks/pages-Politica%2520de%2520Privacidade-485464.json":{"name":"Politica de Privacidade","path":"/institucional/politica-privacidade","blockType":"pages","__resolveType":"website/pages/Page.tsx"},"/.deco/blocks/pages-Product%2520Page-827524.json":{"name":"Product Page","path":"/products/:slug","blockType":"pages","__resolveType":"website/pages/Page.tsx"},"/.deco/blocks/pages-Quem%2520Somos%2520Copy-106248.json":{"name":"Formas de Envio","path":"/institucional/formas-envio","blockType":"pages","__resolveType":"website/pages/Page.tsx"},"/.deco/blocks/pages-Search-571132.json":{"name":"Search","path":"/s","blockType":"pages","__resolveType":"website/pages/Page.tsx"},"/.deco/blocks/pages-Seguran%25C3%25A7a-987276.json":{"name":"Segurança","path":"/institucional/seguranca","blockType":"pages","__resolveType":"website/pages/Page.tsx"},"/.deco/blocks/pages-Start-15553.json":{"name":"Home","path":"/","blockType":"pages","__resolveType":"website/pages/Page.tsx"},"/.deco/blocks/pages-Trocas%2520e%2520Devolu%25C3%25A7%25C3%25B5es-897174.json":{"name":"Trocas e Devoluções","path":"/institucional/trocas-devolucoes","blockType":"pages","__resolveType":"website/pages/Page.tsx"},"/.deco/blocks/Preview%20%2Fsections%2FFooter.tsx.json":{"blockType":"sections","__resolveType":"site/sections/Footer.tsx"},"/.deco/blocks/Preview%20%2Fsections%2FItWorks.tsx.json":{"blockType":"sections","__resolveType":"site/sections/ItWorks.tsx"},"/.deco/blocks/Produtos%20relacionados.json":{"blockType":"sections","__resolveType":"site/sections/Container.tsx"},"/.deco/blocks/Redes%20sociais.json":{"blockType":"sections","__resolveType":"site/sections/Container.tsx"},"/.deco/blocks/Renzi%20CO.json":{"blockType":"sections","__resolveType":"site/sections/Theme/Theme.tsx"},"/.deco/blocks/SearchResults%20Category.json":{"blockType":"sections","__resolveType":"site/sections/Container.tsx"},"/.deco/blocks/Serene%20Coastline.json":{"blockType":"sections","__resolveType":"site/sections/Theme/Theme.tsx"},"/.deco/blocks/site.json":{"blockType":"apps","__resolveType":"site/apps/site.ts"},"/.deco/blocks/Sunset%20Glow.json":{"blockType":"sections","__resolveType":"site/sections/Theme/Theme.tsx"},"/.deco/blocks/Urban%20Chic.json":{"blockType":"sections","__resolveType":"site/sections/Theme/Theme.tsx"}}